{
    "black pepper + cayenne pepper + garlic powder + onion powder + oregano + paprika + thyme": {
        "items": [
            "black pepper",
            "cayenne pepper",
            "garlic powder",
            "onion powder",
            "oregano",
            "paprika",
            "thyme"
        ],
        "count": 39,
        "support": 0.0009805400512897873,
        "support_percentage": "0.10%"
    },
    "black pepper + garlic powder + onion powder + oregano + paprika + salt + thyme": {
        "items": [
            "black pepper",
            "garlic powder",
            "onion powder",
            "oregano",
            "paprika",
            "salt",
            "thyme"
        ],
        "count": 39,
        "support": 0.0009805400512897873,
        "support_percentage": "0.10%"
    },
    "black pepper + cayenne pepper + garlic powder + onion powder + paprika + salt + thyme": {
        "items": [
            "black pepper",
            "cayenne pepper",
            "garlic powder",
            "onion powder",
            "paprika",
            "salt",
            "thyme"
        ],
        "count": 34,
        "support": 0.0008548297883039171,
        "support_percentage": "0.09%"
    },
    "black pepper + cayenne pepper + garlic powder + onion powder + oregano + paprika + salt": {
        "items": [
            "black pepper",
            "cayenne pepper",
            "garlic powder",
            "onion powder",
            "oregano",
            "paprika",
            "salt"
        ],
        "count": 31,
        "support": 0.000779403630512395,
        "support_percentage": "0.08%"
    },
    "black pepper + cayenne pepper + garlic powder + onion powder + oregano + salt + thyme": {
        "items": [
            "black pepper",
            "cayenne pepper",
            "garlic powder",
            "onion powder",
            "oregano",
            "salt",
            "thyme"
        ],
        "count": 30,
        "support": 0.000754261577915221,
        "support_percentage": "0.08%"
    },
    "black pepper + cayenne pepper + garlic powder + oregano + paprika + salt + thyme": {
        "items": [
            "black pepper",
            "cayenne pepper",
            "garlic powder",
            "oregano",
            "paprika",
            "salt",
            "thyme"
        ],
        "count": 31,
        "support": 0.000779403630512395,
        "support_percentage": "0.08%"
    },
    "black pepper + cayenne pepper + onion powder + oregano + paprika + salt + thyme": {
        "items": [
            "black pepper",
            "cayenne pepper",
            "onion powder",
            "oregano",
            "paprika",
            "salt",
            "thyme"
        ],
        "count": 31,
        "support": 0.000779403630512395,
        "support_percentage": "0.08%"
    },
    "cayenne pepper + garlic powder + onion powder + oregano + paprika + salt + thyme": {
        "items": [
            "cayenne pepper",
            "garlic powder",
            "onion powder",
            "oregano",
            "paprika",
            "salt",
            "thyme"
        ],
        "count": 33,
        "support": 0.0008296877357067431,
        "support_percentage": "0.08%"
    }
}